[
  {
    "id": 1,
    "bookingNumber": "BK-20260101-AA1111",
    "scheduledDate": "2026-01-15T10:00:00Z",
    "status": "Completed",
    "description": "تغيير زيت المحرك والفلتر بشكل دوري",
    "totalCost": 150.0,
    "paymentStatus": "Paid",
    "paymentMethod": "Cash",
    "userId": "cust-001",
    "vehicleId": 1,
    "technicianId": "tech-001"
  },
  {
    "id": 2,
    "bookingNumber": "BK-20260115-BB2222",
    "scheduledDate": "2026-02-01T09:00:00Z",
    "status": "Completed",
    "description": "في صوت من الفرامل وبتهز عند الكبح",
    "totalCost": 400.0,
    "paymentStatus": "Paid",
    "paymentMethod": "CreditCard",
    "userId": "cust-002",
    "vehicleId": 3,
    "technicianId": "tech-003"
  },
  {
    "id": 3,
    "bookingNumber": "BK-20260201-CC3333",
    "scheduledDate": "2026-04-20T11:00:00Z",
    "status": "Completed",
    "description": "التكييف مش بيبرد وفي صوت من الكمبروسر",
    "totalCost": 350.0,
    "paymentStatus": "Paid",
    "paymentMethod": "Cash",
    "userId": "cust-003",
    "vehicleId": 4,
    "technicianId": "tech-008"
  },
  {
    "id": 4,
    "bookingNumber": "BK-20260410-DD4444",
    "scheduledDate": "2026-05-01T10:00:00Z",
    "status": "InProgress",
    "description": "العربية بتهز على سرعة 80 وما بتبقاش ثابتة على الطريق",
    "totalCost": 180.0,
    "paymentStatus": "Pending",
    "paymentMethod": "Cash",
    "userId": "cust-001",
    "vehicleId": 2,
    "technicianId": "tech-006"
  },
  {
    "id": 5,
    "bookingNumber": "BK-20260415-EE5555",
    "scheduledDate": "2026-05-05T14:00:00Z",
    "status": "WaitingClientApproval",
    "description": "البطارية بتفضى بسرعة والعربية مش بتشتغل من أول مرة",
    "totalCost": 150.0,
    "paymentStatus": "Pending",
    "paymentMethod": "CreditCard",
    "userId": "cust-004",
    "vehicleId": 5,
    "technicianId": "tech-007"
  },
  {
    "id": 6,
    "bookingNumber": "BK-20260416-FF6666",
    "scheduledDate": "2026-05-10T09:00:00Z",
    "status": "Pending",
    "description": "محتاج فحص المحرك الإلكتروني ظهرت لمبة check engine",
    "totalCost": 200.0,
    "paymentStatus": "Pending",
    "paymentMethod": "Cash",
    "userId": "cust-002",
    "vehicleId": 3,
    "technicianId": null
  }
]